<?xml version="1.0" encoding="UTF-8"?>
<!DOCTYPE coverity SYSTEM "coverity_config.dtd">
<coverity>
<!-- THIS FILE IS AUTOMATICALLY GENERATED - YOU MAY ADD XML ENTITIES -->
<!-- TO UPDATE THE COMPILER CONFIGURATION AFTER THE begin_command_line_config CLOSING TAG. -->
    <cit_version>1</cit_version>
    <config>
      <build>
        <compiler>
          <template_compiler>true</template_compiler>
          <comp_name>cc</comp_name>
          <comp_translator>gcc</comp_translator>
          <comp_lang>C</comp_lang>
          <comp_generic>gnu</comp_generic>
        </compiler>
        <options>
          <id>gcc-cc-.*</id>
          <opt_preinclude_file>$CONFIGDIR$/../user_nodefs.h</opt_preinclude_file>
          <begin_command_line_config></begin_command_line_config>
        </options>
        <options>
          <id>g++-cc-.*</id>
          <opt_preinclude_file>$CONFIGDIR$/../user_nodefs.h</opt_preinclude_file>
          <begin_command_line_config></begin_command_line_config>
        </options>
        <options>
          <id>g++cc-cc-.*</id>
          <opt_preinclude_file>$CONFIGDIR$/../user_nodefs.h</opt_preinclude_file>
          <begin_command_line_config></begin_command_line_config>
        </options>
      </build>
    </config>
    <md5>47a502735554e6c25b61a8bf08e5fa6d</md5>
</coverity>

